README.md
setup.py
pygenalg/__init__.py
pygenalg.egg-info/PKG-INFO
pygenalg.egg-info/SOURCES.txt
pygenalg.egg-info/dependency_links.txt
pygenalg.egg-info/top_level.txt
pygenalg/basics/__init__.py
pygenalg/basics/basicComponent.py
pygenalg/basics/customLogger.py