Metadata-Version: 2.1
Name: pygenalg
Version: 0.0.0
Summary: Python genetic algorithm
Home-page: https://github.com/StephenMal/PyGenAlg
Author: Stephen Maldonado
Author-email: PyGenAlg@stephenmal.com
License: UNKNOWN
Platform: UNKNOWN
Classifier: Development Status :: 1 - Planning
Classifier: Programming Language :: Python :: 3 :: Only
Classifier: Topic :: Utilities
